.gitignore
cgraphlib/__init__.py
cgraphlib/cgraphlib.c
taskade-0.0.1.dist-info/METADATA
taskade-0.0.1.dist-info/WHEEL
taskade-0.0.1.dist-info/licenses/LICENSE
taskade/__init__.py
taskade/_decorator.py
taskade/_exceptions.py
taskade/_execution.py
taskade/_types.py
taskade/cgraphlib.cpython-310-x86_64-linux-gnu.so
taskade/cgraphlib.pyi
taskade-0.0.1.dist-info/RECORD
