Metadata-Version: 2.1
Name: taskade
Version: 0.0.1
Summary: A DAG framework written in std python
Author-Email: Alex Epstein <alexanderepstein@tuta.io>
License: MIT
Requires-Python: >=3.8
Provides-Extra: docs
Requires-Dist: mkdocs>=1.6.0; extra == "docs"
Requires-Dist: mkdocs-material>=9.5.31; extra == "docs"
Requires-Dist: mkdocs-gen-files>=0.5.0; extra == "docs"
Requires-Dist: mkdocstrings>=0.25.2; extra == "docs"
Requires-Dist: mkdocs-literate-nav>=0.6.1; extra == "docs"
Requires-Dist: mkdocs-section-index>=0.3.9; extra == "docs"
Requires-Dist: mkdocs-autorefs>=1.0.1; extra == "docs"
Requires-Dist: mkdocstrings-python>=1.10.8; extra == "docs"
Requires-Dist: mkdocs-coverage>=1.1.0; extra == "docs"
Requires-Dist: mkdocs-git-revision-date-localized-plugin>=1.2.6; extra == "docs"
Requires-Dist: mkdocs-git-authors-plugin>=0.9.0; extra == "docs"
